{
  "version": 1,
  "paths": {
    "/addTask/{listId}": {
      "name": "/addTask/{listId}",
      "lambdaFunction": "addTaskToList",
      "permissions": {
        "setting": "open"
      }
    },
    "/addCollaborator": {
      "name": "/addCollaborator",
      "lambdaFunction": "addCollaboratorToList",
      "permissions": {
        "setting": "open"
      }
    },
    "/tasks": {
      "name": "/tasks",
      "lambdaFunction": "modifyTask",
      "permissions": {
        "setting": "open"
      }
    },
    "/lists": {
      "name": "/lists",
      "lambdaFunction": "todoListHandler",
      "permissions": {
        "setting": "open"
      }
    },
    "/lists/{listId}": {
      "name": "/lists/{listId}",
      "lambdaFunction": "tasksHandler",
      "permissions": {
        "setting": "open"
      }
    },
    "/profile/{userId}": {
      "name": "/profile/{userId}",
      "lambdaFunction": "userProfileHandler",
      "permissions": {
        "setting": "open"
      }
    }
  }
}